{
  "id": "d9d92249-6bb2-4972-9b8a-ae4eb1806049",
  "prevId": "00000000-0000-0000-0000-000000000000",
  "version": "5",
  "dialect": "pg",
  "tables": {
    "quotes": {
      "name": "quotes",
      "schema": "",
      "columns": {
        "id": {
          "name": "id",
          "type": "uuid",
          "primaryKey": true,
          "notNull": true,
          "default": "gen_random_uuid()"
        },
        "premium": {
          "name": "premium",
          "type": "integer",
          "primaryKey": false,
          "notNull": false
        },
        "limit": {
          "name": "limit",
          "type": "integer",
          "primaryKey": false,
          "notNull": false
        },
        "deductible": {
          "name": "deductible",
          "type": "integer",
          "primaryKey": false,
          "notNull": false
        },
        "created_at": {
          "name": "created_at",
          "type": "timestamp with time zone",
          "primaryKey": false,
          "notNull": false,
          "default": "now()"
        },
        "updated_at": {
          "name": "updated_at",
          "type": "timestamp with time zone",
          "primaryKey": false,
          "notNull": false,
          "default": "now()"
        }
      },
      "indexes": {},
      "foreignKeys": {},
      "compositePrimaryKeys": {},
      "uniqueConstraints": {}
    }
  },
  "enums": {},
  "schemas": {},
  "_meta": {
    "columns": {},
    "schemas": {},
    "tables": {}
  }
}